README.rst
setup.py
leetcode_dl/__init__.py
leetcode_dl/__main__.py
leetcode_dl/const.py
leetcode_dl/leetcode.py
leetcode_dl/model.py
leetcode_dl/utils.py
leetcode_dl.egg-info/PKG-INFO
leetcode_dl.egg-info/SOURCES.txt
leetcode_dl.egg-info/dependency_links.txt
leetcode_dl.egg-info/entry_points.txt
leetcode_dl.egg-info/requires.txt
leetcode_dl.egg-info/top_level.txt
leetcode_dl_cli/__init__.py
leetcode_dl_cli/cli.py
leetcode_dl_cli/main.py