Metadata-Version: 1.1
Name: leetcode-dl
Version: 0.1.3
Summary: Command-line program to download solutions from leetcode.com
Home-page: http://github.com/bonfy/leetcode-dl
Author: bonfy
Author-email: foreverbonfy@163.com
License: MIT License
Download-URL: https://pypi.python.org/pypi/leetcode-dl
Keywords: leetcode download
Platform: any
